bagit_profile.py
bagit_profile-1.3.1.data/scripts/bagit_profile.py
bagit_profile-1.3.1.dist-info/LICENSE
bagit_profile-1.3.1.dist-info/METADATA
bagit_profile-1.3.1.dist-info/WHEEL
bagit_profile-1.3.1.dist-info/top_level.txt
bagit_profile-1.3.1.dist-info/RECORD
