Metadata-Version: 1.1
Name: bagit_profile
Version: 1.3.1
Summary: 
Home-page: https://github.com/bagit-profiles/bagit-profiles-validator
Author: Mark Jordan, Nick Ruest
Author-email: mjordan@sfu.ca, ruestn@gmail.com
License: CC0
Platform: POSIX
Classifier: License :: Public Domain
Classifier: Intended Audience :: Developers
Classifier: Topic :: Communications :: File Sharing
Classifier: Topic :: Software Development :: Libraries :: Python Modules
Classifier: Topic :: System :: Filesystems
Classifier: Topic :: Utilities
Classifier: Programming Language :: Python :: 2.7
Classifier: Programming Language :: Python :: 3.4
Classifier: Programming Language :: Python :: 3.5
Classifier: Programming Language :: Python :: 3.6
Classifier: Programming Language :: Python :: 3.7
